planegeometry/__init__.py
planegeometry/geometry.py
planegeometry/internal.py
pyplanegeometry-0.1.0.dist-info/LICENSE
pyplanegeometry-0.1.0.dist-info/WHEEL
pyplanegeometry-0.1.0.dist-info/METADATA
pyplanegeometry-0.1.0.dist-info/RECORD
