Metadata-Version: 2.1
Name: pyplanegeometry
Version: 0.1.0
Summary: Plane geometry
Home-page: https://github.com/stla/PyPlaneGeometry
License: GPL-3.0-only
Keywords: plane geometry,geometry
Author: Stéphane Laurent
Author-email: laurent_step@outlook.fr
Requires-Python: >=3.8,<3.10
Classifier: License :: OSI Approved :: GNU General Public License v3 (GPLv3)
Classifier: Programming Language :: Python :: 3
Classifier: Programming Language :: Python :: 3.8
Classifier: Programming Language :: Python :: 3.9
Provides-Extra: docs
Requires-Dist: numpy (>=1.24.2,<2.0.0)
Requires-Dist: sphinx (>=5.3.0,<6.0.0); extra == "docs"
Requires-Dist: sphinx-rtd-theme (>=1.1.1,<2.0.0); extra == "docs"
Requires-Dist: sphinxcontrib-restbuilder (>=0.3,<0.4); extra == "docs"
Project-URL: Documentation, https://pyplanegeometry.readthedocs.io/en/latest/
